webhookbin/__init__.py
webhookbin-1.0.1.dist-info/LICENSE
webhookbin-1.0.1.dist-info/METADATA
webhookbin-1.0.1.dist-info/WHEEL
webhookbin-1.0.1.dist-info/top_level.txt
webhookbin-1.0.1.dist-info/RECORD
