Metadata-Version: 2.1
Name: webhookbin
Version: 1.0.1
Summary: Python library for webhookbin.net
Home-page: https://github.com/Sumiza/webhookbin-library/
Author: Sumiza
Author-email: sumiza@gmail.com
Project-URL: Bug Tracker, https://github.com/Sumiza/webhookbin-library/issues
Classifier: Programming Language :: Python :: 3.9
Classifier: Programming Language :: Python :: 3.10
Classifier: License :: OSI Approved :: GNU General Public License v3 (GPLv3)
Classifier: Operating System :: OS Independent
Requires-Python: >=3.7
License-File: LICENSE
Requires-Dist: requests
